restful_ben/__init__.py
restful_ben/auth.py
restful_ben/resources.py
restful_ben/test_utils.py
restful_ben-0.4.2.dist-info/METADATA
restful_ben-0.4.2.dist-info/RECORD
restful_ben-0.4.2.dist-info/WHEEL
restful_ben-0.4.2.dist-info/top_level.txt
