Metadata-Version: 2.1
Name: restful-ben
Version: 0.4.2
Summary: A composable SQLAlchemy based RESTful API library.
Home-page: https://github.com/awm33/restful-ben
Author: Andrew Madonna
License: UNKNOWN
Platform: UNKNOWN
Classifier: Programming Language :: Python :: 3
Classifier: License :: OSI Approved :: MIT License
Classifier: Operating System :: OS Independent
Requires-Dist: argon2-cffi (==16.3.0)
Requires-Dist: cryptography (==2.3)
Requires-Dist: Flask (==0.12.2)
Requires-Dist: Flask-Login (==0.4.0)
Requires-Dist: Flask-RESTful (==0.3.6)
Requires-Dist: Flask-SQLAlchemy (==2.2)
Requires-Dist: marshmallow (==2.13.5)
Requires-Dist: marshmallow-sqlalchemy (==0.13.1)
Requires-Dist: passlib (==1.7.1)
Requires-Dist: psycopg2 (==2.7.1)
Requires-Dist: python-dateutil (==2.6.0)
